sierra/__init__.py
sierra/bullets_and_lists.py
sierra/custom_tags.py
sierra/main_htm.py
sierra/tTags.py
sierra/table.py
sierra/tags.py
sierra/write.py
sierra-2.4.0.dist-info/LICENSE
sierra-2.4.0.dist-info/METADATA
sierra-2.4.0.dist-info/WHEEL
sierra-2.4.0.dist-info/top_level.txt
sierra-2.4.0.dist-info/zip-safe
sierra-2.4.0.dist-info/RECORD
