Metadata-Version: 2.1
Name: sierra
Version: 2.4.0
Summary: Sierra is a Python library to write HTML and CSS in pure Python using the DOM API in a simple yet elegant manner
Home-page: http://github.com/BrainStormYourWayIn/sierra
Author: Pranav and Siddhesh
Author-email: brainstormyourwayin@gmail.com
License: Apache Software License
Project-URL: Bug Tracker, https://github.com/BrainStormYourWayIn/sierra/issues
Project-URL: Documentation, https://brainstormyourwayin.github.io/sierra.github.io/
Keywords: css,html,web development,web framework,templating,python to HTML,python to CSS,jinja,django
Platform: UNKNOWN
Classifier: Development Status :: 5 - Production/Stable
Classifier: License :: OSI Approved :: Apache Software License
Classifier: Natural Language :: English
Classifier: Operating System :: OS Independent
Classifier: Programming Language :: Python :: 3.4
Classifier: Programming Language :: Python :: 3.5
Classifier: Programming Language :: Python :: 3.6
Classifier: Programming Language :: Python :: 3.7
Classifier: Programming Language :: Python :: 3.8
Classifier: Programming Language :: Python :: 3.9
Classifier: Programming Language :: Python :: 3.10
Classifier: Programming Language :: Python :: 3 :: Only
Classifier: Programming Language :: Python :: Implementation
Classifier: Topic :: Software Development :: Libraries :: Application Frameworks
Classifier: Topic :: Software Development :: Libraries :: Python Modules
Requires-Python: >=3.4
License-File: LICENSE
Requires-Dist: pandas
Requires-Dist: beautifulsoup4
